{
  "Pepperoni": "S_PIZZA|Topping|P",
  "Brooklyn Pepperoni": "S_PIZZA|Topping|Xp",
  "Sausage": "S_PIZZA|Topping|S",
  "Beef Crumble": "S_PIZZA|Topping|B",
  "Ham": "S_PIZZA|Topping|H",
  "Bacon": "S_PIZZA|Topping|K",
  "Chicken*": "S_PIZZA|Topping|D",
  "Philly Steak*": "S_PIZZA|Topping|St",
  "Cheddar*": "S_PIZZA|Topping|E",
  "Feta*": "S_PIZZA|Topping|Fe",
  "Parmesan Asiago*": "S_PIZZA|Topping|Pa",
  "Provolone": "S_PIZZA|Topping|Cp",
  "Hot Banana Peppers": "S_PIZZA|Topping|Z",
  "Black Olives": "S_PIZZA|Topping|R",
  "Green Olives": "S_PIZZA|Topping|V",
  "Green Pepper": "S_PIZZA|Topping|G",
  "Mushroom": "S_PIZZA|Topping|M",
  "Pineapple": "S_PIZZA|Topping|N",
  "Onion": "S_PIZZA|Topping|O",
  "Tomatoes": "S_PIZZA|Topping|T",
  "Jalapeno Peppers": "S_PIZZA|Topping|J",
  "Baby Spinach": "S_PIZZA|Topping|Sp",
  "Roasted Red Peppers": "S_PIZZA|Topping|Rp"
}
